yasod/__init__.py
yasod/common.py
yasod/exceptions.py
yasod/models.py
yasod/yasod.py
yasod-0.1.1.dist-info/LICENSE
yasod-0.1.1.dist-info/WHEEL
yasod-0.1.1.dist-info/METADATA
yasod-0.1.1.dist-info/RECORD
